{
"autoplayBgm":true,"autoplayBgs":false,"battleback1Name":"Wood1","battleback2Name":"Room1","bgm":{"name":"Castle","pan":0,"pitch":100,"volume":90},"bgs":{"name":"","pan":0,"pitch":100,"volume":90},"disableDashing":true,"displayName":"","encounterList":[],"encounterStep":30,"height":7,"note":"","parallaxLoopX":false,"parallaxLoopY":false,"parallaxName":"","parallaxShow":true,"parallaxSx":0,"parallaxSy":0,"scrollType":0,"specifyBattleback":true,"tilesetId":3,"width":7,
"data":[6036,6060,6060,6060,6060,6060,6040,6056,2850,2836,2836,2836,2852,6048,6056,2832,2816,2816,2816,2840,6048,6056,2832,2816,2816,2816,2840,6048,6056,2832,2816,2816,2816,2840,6048,6056,2856,2844,2828,2844,2854,6048,6034,6052,6068,2848,6066,6052,6033,0,0,0,0,0,0,0,0,0,0,0,0,0,0,0,0,0,0,0,0,0,0,0,0,0,0,0,0,0,0,0,0,0,0,0,0,0,0,0,0,0,0,0,0,0,0,0,0,0,0,0,0,0,0,0,0,0,0,0,0,0,0,0,0,0,0,0,0,0,0,0,0,0,0,0,0,0,0,0,0,0,0,96,0,0,0,0,0,0,0,0,0,0,0,0,0,0,0,0,0,0,0,0,0,0,0,53,54,55,50,51,0,0,61,62,63,58,59,0,0,0,0,0,0,0,0,0,0,0,0,0,263,0,0,0,0,0,0,104,0,0,0,0,0,0,0,0,0,0,0,0,0,0,0,0,7,3,3,3,3,0,0,5,0,0,0,0,0,0,5,0,0,0,0,0,0,5,0,0,0,0,0,0,5,0,0,0,0,0,0,0,0,0,0,0,0,0,0,0,0,0,0,0,0,0,0,0,0,0,0,0,0,0,0,0,0,0,0,0,0,0,0,0,0,0,0,0,0,0,0,0,0,0,0,0,0,0,0,0,0,0,0,0,0,0],
"events":[
null,
{"id":1,"name":"EV001","note":"","pages":[{"conditions":{"actorId":1,"actorValid":false,"itemId":1,"itemValid":false,"selfSwitchCh":"A","selfSwitchValid":false,"switch1Id":1,"switch1Valid":false,"switch2Id":1,"switch2Valid":false,"variableId":1,"variableValid":false,"variableValue":0},"directionFix":false,"image":{"characterIndex":0,"characterName":"","direction":2,"pattern":0,"tileId":0},"list":[{"code":101,"indent":0,"parameters":["",0,0,2]},{"code":401,"indent":0,"parameters":["Cosas de un viejo almacen"]},{"code":0,"indent":0,"parameters":[]}],"moveFrequency":3,"moveRoute":{"list":[{"code":0,"parameters":[]}],"repeat":true,"skippable":false,"wait":false},"moveSpeed":3,"moveType":0,"priorityType":1,"stepAnime":false,"through":false,"trigger":1,"walkAnime":true}],"x":1,"y":2},
{"id":2,"name":"EV002","note":"","pages":[{"conditions":{"actorId":1,"actorValid":false,"itemId":1,"itemValid":false,"selfSwitchCh":"A","selfSwitchValid":false,"switch1Id":1,"switch1Valid":false,"switch2Id":1,"switch2Valid":false,"variableId":1,"variableValid":false,"variableValue":0},"directionFix":false,"image":{"characterIndex":0,"characterName":"","direction":2,"pattern":0,"tileId":0},"list":[{"code":101,"indent":0,"parameters":["",0,0,2]},{"code":401,"indent":0,"parameters":["Cosas de un viejo almacen"]},{"code":0,"indent":0,"parameters":[]}],"moveFrequency":3,"moveRoute":{"list":[{"code":0,"parameters":[]}],"repeat":true,"skippable":false,"wait":false},"moveSpeed":3,"moveType":0,"priorityType":1,"stepAnime":false,"through":false,"trigger":1,"walkAnime":true}],"x":2,"y":2},
{"id":3,"name":"EV003","note":"","pages":[{"conditions":{"actorId":1,"actorValid":false,"itemId":1,"itemValid":false,"selfSwitchCh":"A","selfSwitchValid":false,"switch1Id":1,"switch1Valid":false,"switch2Id":1,"switch2Valid":false,"variableId":1,"variableValid":false,"variableValue":0},"directionFix":false,"image":{"characterIndex":0,"characterName":"","direction":2,"pattern":0,"tileId":0},"list":[{"code":101,"indent":0,"parameters":["",0,0,2]},{"code":401,"indent":0,"parameters":["Cosas de un viejo almacen"]},{"code":0,"indent":0,"parameters":[]}],"moveFrequency":3,"moveRoute":{"list":[{"code":0,"parameters":[]}],"repeat":true,"skippable":false,"wait":false},"moveSpeed":3,"moveType":0,"priorityType":1,"stepAnime":false,"through":false,"trigger":1,"walkAnime":true}],"x":3,"y":2},
{"id":4,"name":"EV004","note":"","pages":[{"conditions":{"actorId":1,"actorValid":false,"itemId":1,"itemValid":false,"selfSwitchCh":"A","selfSwitchValid":false,"switch1Id":1,"switch1Valid":false,"switch2Id":1,"switch2Valid":false,"variableId":1,"variableValid":false,"variableValue":0},"directionFix":false,"image":{"characterIndex":0,"characterName":"","direction":2,"pattern":0,"tileId":0},"list":[{"code":101,"indent":0,"parameters":["",0,0,2]},{"code":401,"indent":0,"parameters":["Cosas de un viejo almacen"]},{"code":0,"indent":0,"parameters":[]}],"moveFrequency":3,"moveRoute":{"list":[{"code":0,"parameters":[]}],"repeat":true,"skippable":false,"wait":false},"moveSpeed":3,"moveType":0,"priorityType":1,"stepAnime":false,"through":false,"trigger":1,"walkAnime":true}],"x":5,"y":2},
{"id":5,"name":"EV005","note":"","pages":[{"conditions":{"actorId":1,"actorValid":false,"itemId":1,"itemValid":false,"selfSwitchCh":"A","selfSwitchValid":false,"switch1Id":1,"switch1Valid":false,"switch2Id":1,"switch2Valid":false,"variableId":1,"variableValid":false,"variableValue":0},"directionFix":false,"image":{"characterIndex":0,"characterName":"","direction":2,"pattern":0,"tileId":0},"list":[{"code":101,"indent":0,"parameters":["",0,0,2]},{"code":401,"indent":0,"parameters":["Esta Cerrado con Llave..."]},{"code":0,"indent":0,"parameters":[]}],"moveFrequency":3,"moveRoute":{"list":[{"code":0,"parameters":[]}],"repeat":true,"skippable":false,"wait":false},"moveSpeed":3,"moveType":0,"priorityType":1,"stepAnime":false,"through":false,"trigger":1,"walkAnime":true},{"conditions":{"actorId":1,"actorValid":false,"itemId":10,"itemValid":true,"selfSwitchCh":"A","selfSwitchValid":false,"switch1Id":1,"switch1Valid":false,"switch2Id":1,"switch2Valid":false,"variableId":1,"variableValid":false,"variableValue":0},"directionFix":false,"image":{"characterIndex":0,"characterName":"","direction":2,"pattern":0,"tileId":0},"list":[{"code":101,"indent":0,"parameters":["",0,0,2]},{"code":401,"indent":0,"parameters":["La llave misteriosa abre la puerta"]},{"code":101,"indent":0,"parameters":["Nature",2,0,2]},{"code":401,"indent":0,"parameters":["*El gallo Tulgar aparece*"]},{"code":401,"indent":0,"parameters":["Coaaaaah Coo! Coaaah! Co CoAH!"]},{"code":301,"indent":0,"parameters":[0,5,true,false]},{"code":601,"indent":0,"parameters":[]},{"code":101,"indent":1,"parameters":["rediant",0,0,2]},{"code":401,"indent":1,"parameters":["Tulgar..."]},{"code":101,"indent":1,"parameters":["Kyoros true",0,0,2]},{"code":401,"indent":1,"parameters":["No habia nada que pudiesemos hacer... nuestras vidas"]},{"code":401,"indent":1,"parameters":["estaban en juego"]},{"code":0,"indent":1,"parameters":[]},{"code":602,"indent":0,"parameters":[]},{"code":101,"indent":1,"parameters":["Kyoros true",0,0,2]},{"code":401,"indent":1,"parameters":["*Click*"]},{"code":401,"indent":1,"parameters":["La puerta se ah cerrado para siempre, ese monstruo es"]},{"code":401,"indent":1,"parameters":["demasiado poderoso, jamas debemos volver a despertarlo"]},{"code":101,"indent":1,"parameters":["Neo True",0,0,2]},{"code":401,"indent":1,"parameters":["Lo que hubiese dado por probar una patita"]},{"code":401,"indent":1,"parameters":["de pollo..."]},{"code":0,"indent":1,"parameters":[]},{"code":604,"indent":0,"parameters":[]},{"code":0,"indent":0,"parameters":[]}],"moveFrequency":3,"moveRoute":{"list":[{"code":0,"parameters":[]}],"repeat":true,"skippable":false,"wait":false},"moveSpeed":3,"moveType":0,"priorityType":1,"stepAnime":false,"through":false,"trigger":1,"walkAnime":true}],"x":4,"y":2},
{"id":6,"name":"EV006","note":"","pages":[{"conditions":{"actorId":1,"actorValid":false,"itemId":1,"itemValid":false,"selfSwitchCh":"A","selfSwitchValid":false,"switch1Id":1,"switch1Valid":false,"switch2Id":1,"switch2Valid":false,"variableId":1,"variableValid":false,"variableValue":0},"directionFix":false,"image":{"characterIndex":0,"characterName":"","direction":2,"pattern":0,"tileId":0},"list":[{"code":201,"indent":0,"parameters":[0,8,1,32,0,0]},{"code":121,"indent":0,"parameters":[26,26,0]},{"code":0,"indent":0,"parameters":[]}],"moveFrequency":3,"moveRoute":{"list":[{"code":0,"parameters":[]}],"repeat":true,"skippable":false,"wait":false},"moveSpeed":3,"moveType":0,"priorityType":0,"stepAnime":false,"through":false,"trigger":1,"walkAnime":true}],"x":3,"y":6},
null
]
}