[
null,
{"id":1,"animationId":9,"description":"La espada de la rana puede exterminar cualquier ser\nhumanoide es de las mas fuertes jamas vista","etypeId":1,"traits":[{"code":31,"dataId":1,"value":0},{"code":22,"dataId":0,"value":0},{"code":11,"dataId":1,"value":1.5},{"code":22,"dataId":2,"value":0.5}],"iconIndex":120,"name":"Espada de la Rana","note":"","params":[300,50,200,0,100,0,0,0],"price":5000,"wtypeId":2},
{"id":2,"animationId":6,"description":"","etypeId":1,"traits":[{"code":31,"dataId":1,"value":0},{"code":22,"dataId":0,"value":0}],"iconIndex":99,"name":"Hacha","note":"","params":[0,0,10,0,0,0,0,0],"price":500,"wtypeId":4},
{"id":3,"animationId":1,"description":"","etypeId":1,"traits":[{"code":31,"dataId":1,"value":0},{"code":22,"dataId":0,"value":0}],"iconIndex":101,"name":"Vara","note":"","params":[0,0,10,0,0,0,0,0],"price":500,"wtypeId":6},
{"id":4,"animationId":11,"description":"","etypeId":1,"traits":[{"code":31,"dataId":1,"value":0},{"code":22,"dataId":0,"value":0}],"iconIndex":102,"name":"Arco","note":"","params":[0,0,10,0,0,0,0,0],"price":500,"wtypeId":7},
{"id":5,"animationId":6,"description":"Espada del Legendario Paladin Telgar","etypeId":1,"traits":[{"code":31,"dataId":1,"value":0},{"code":22,"dataId":0,"value":0}],"iconIndex":107,"name":"Espada Telgar","note":"","params":[0,0,25,0,15,0,10,0],"price":4900,"wtypeId":2},
{"id":6,"animationId":2,"description":"Espada con escamas de Dragon, habilidades Secretas tiene ocultas","etypeId":1,"traits":[{"code":31,"dataId":1,"value":0},{"code":22,"dataId":0,"value":0}],"iconIndex":112,"name":"Espada Dragon","note":"","params":[0,0,30,0,10,5,10,0],"price":8000,"wtypeId":2},
{"id":7,"animationId":11,"description":"Lanza que es mas fuerte al proteger","etypeId":1,"traits":[{"code":31,"dataId":1,"value":0},{"code":22,"dataId":0,"value":0}],"iconIndex":107,"name":"Lanza Feroz","note":"","params":[0,0,35,0,0,0,0,0],"price":0,"wtypeId":12},
{"id":8,"animationId":24,"description":"La espada del Gran Guerrero Khal El","etypeId":1,"traits":[{"code":31,"dataId":1,"value":0},{"code":22,"dataId":0,"value":0}],"iconIndex":97,"name":"Espada Astul","note":"","params":[0,0,30,0,0,0,0,0],"price":7000,"wtypeId":2},
{"id":9,"animationId":26,"description":"Daga tipo Estilete, especial para perforar a los \nenemigos","etypeId":1,"traits":[{"code":31,"dataId":1,"value":0},{"code":22,"dataId":0,"value":0},{"code":22,"dataId":0,"value":0.59}],"iconIndex":96,"name":"Daga de Asesino","note":"","params":[0,0,20,0,0,0,0,0],"price":34,"wtypeId":1},
{"id":10,"animationId":23,"description":"La espada del legendario caballero del pais del Viento","etypeId":1,"traits":[{"code":31,"dataId":1,"value":0},{"code":22,"dataId":0,"value":0},{"code":31,"dataId":7,"value":1}],"iconIndex":97,"name":"Espada de Remiant","note":"","params":[0,0,150,0,0,0,0,0],"price":80000,"wtypeId":2},
{"id":11,"animationId":31,"description":"Hacha de oso de Mithiril practicamente indestructible","etypeId":1,"traits":[{"code":31,"dataId":1,"value":0},{"code":22,"dataId":0,"value":0}],"iconIndex":99,"name":"Hacha de Oso de Mithril","note":"","params":[0,0,70,0,10,0,0,0],"price":120000,"wtypeId":4},
{"id":12,"animationId":29,"description":"Arco Elfico +30","etypeId":1,"traits":[{"code":11,"dataId":1,"value":1},{"code":22,"dataId":0,"value":0},{"code":33,"dataId":0,"value":10}],"iconIndex":102,"name":"Arco Elfico","note":"","params":[0,0,30,0,0,0,0,0],"price":400,"wtypeId":7},
{"id":13,"animationId":6,"description":"2 poderosas hachas para usar en combate","etypeId":1,"traits":[{"code":31,"dataId":1,"value":0},{"code":22,"dataId":0,"value":0},{"code":53,"dataId":2,"value":1}],"iconIndex":99,"name":"Juego de Hachas Milenarias","note":"","params":[0,0,70,0,0,0,0,0],"price":340,"wtypeId":4}
]